README.md
setup.py
django_cas_binder/__init__.py
django_cas_binder/admin.py
django_cas_binder/assign_universal_ids.py
django_cas_binder/auth_backends.py
django_cas_binder/create_user_and_casuser.py
django_cas_binder/models.py
django_cas_binder/oic_rest_auth.py
django_cas_binder/setup_django.py
django_cas_binder/utils.py
django_cas_binder.egg-info/PKG-INFO
django_cas_binder.egg-info/SOURCES.txt
django_cas_binder.egg-info/dependency_links.txt
django_cas_binder.egg-info/requires.txt
django_cas_binder.egg-info/top_level.txt
django_cas_binder/migrations/0001_initial.py
django_cas_binder/migrations/__init__.py