Metadata-Version: 1.1
Name: django-cas-binder
Version: 2.0.0
Summary: A thin wrapper around django-cas-ng that allows to use identifier other than username.
Home-page: UNKNOWN
Author: Quantitative Engineering Design Inc.
Author-email: UNKNOWN
License: UNKNOWN
Platform: UNKNOWN
Classifier: Environment :: Web Environment
Classifier: Intended Audience :: Developers
Classifier: License :: OSI Approved :: BSD License
Classifier: Operating System :: OS Independent
Classifier: Programming Language :: Python :: 2.7
Classifier: Programming Language :: Python :: 3
Classifier: Programming Language :: Python :: 3.2
Classifier: Programming Language :: Python :: 3.3
Classifier: Programming Language :: Python :: 3.4
Classifier: Programming Language :: Python :: 3.5
Classifier: Framework :: Django
